threadgroup/__init__.py
threadgroup/structs.py
threadgroup/threadgroup.py
threadgroup_lib-1.2.1.dist-info/LICENSE
threadgroup_lib-1.2.1.dist-info/METADATA
threadgroup_lib-1.2.1.dist-info/WHEEL
threadgroup_lib-1.2.1.dist-info/top_level.txt
threadgroup_lib-1.2.1.dist-info/RECORD
