Metadata-Version: 2.1
Name: threadgroup-lib
Version: 1.2.1
Summary: A package that sets up thread-groups to run methods concurrently that can run concurrently in a relatively simple and intuitive way.
Home-page: https://github.com/data-ductus/threadgroup-lib
Author: Chloe Holst
Author-email: chloe.holst@dataductus.se
License: Apache 2.0
Classifier: License :: OSI Approved :: Apache Software License
Classifier: Programming Language :: Python :: 3
Classifier: Programming Language :: Python :: 3.8
License-File: LICENSE
